versionman/__init__.py
versionman/pep440_semver.py
versionman/exception/__init__.py
versionman/exception/base.py
versionman/exception/pep440_semver.py
versionman-0.1.1.dist-info/METADATA
versionman-0.1.1.dist-info/WHEEL
versionman-0.1.1.dist-info/top_level.txt
versionman-0.1.1.dist-info/RECORD
