Metadata-Version: 2.2
Name: VersionMan
Version: 0.1.1
Requires-Python: >=3.10
Requires-Dist: packaging<25,>=23.2
